csrf/__init__.py
csrf/csrf.py
csrf-0.1b1.dist-info/zip-safe
csrf-0.1b1.dist-info/WHEEL
csrf-0.1b1.dist-info/METADATA
csrf-0.1b1.dist-info/metadata.json
csrf-0.1b1.dist-info/top_level.txt
csrf-0.1b1.dist-info/DESCRIPTION.rst
csrf-0.1b1.dist-info/RECORD
